Metadata-Version: 2.1
Name: hpass
Version: 0.2.0
Summary: A simple password management tool
Home-page: https://github.com/hekaiyou/hpass
Author: Kaiyou He
Author-email: hky0313@outlook.com
License: UNKNOWN
Keywords: password pass hpass hello
Platform: any
Classifier: Development Status :: 3 - Alpha
Classifier: Intended Audience :: Developers
Classifier: Topic :: Desktop Environment :: File Managers
Classifier: License :: OSI Approved :: MIT License
Classifier: Programming Language :: Python :: 3
Classifier: Programming Language :: Python :: 3.5
Classifier: Programming Language :: Python :: 3.6
Classifier: Programming Language :: Python :: 3.7
Classifier: Programming Language :: Python :: 3.8
Classifier: Programming Language :: Python
Classifier: Operating System :: OS Independent
